bilkom.py
bilkom-0.0.4.dist-info/LICENSE
bilkom-0.0.4.dist-info/WHEEL
bilkom-0.0.4.dist-info/METADATA
bilkom-0.0.4.dist-info/RECORD
