Metadata-Version: 2.1
Name: bilkom
Version: 0.0.4
Summary: BILKOM train info
Author-email: wnuczek <mail@pawelwnuk.pl>
Classifier: License :: OSI Approved :: MIT License
Project-URL: Home, https://github.com/wnuczek/bilkom
